aio_easy_rabbit/__init__.py
aio_easy_rabbit/connection.py
aio_easy_rabbit/consumer_registry.py
aio_easy_rabbit/decorators.py
aio_easy_rabbit/producers.py
aio_easy_rabbit-0.0.1.dist-info/LICENSE
aio_easy_rabbit-0.0.1.dist-info/METADATA
aio_easy_rabbit-0.0.1.dist-info/WHEEL
aio_easy_rabbit-0.0.1.dist-info/top_level.txt
aio_easy_rabbit-0.0.1.dist-info/RECORD
