Metadata-Version: 2.1
Name: aio-easy-rabbit
Version: 0.0.1
Summary: A simple rabbitmq client for asyncio applications based on the awesome aio-pika library!
Author-email: Bo Stokholm <the.one.nachash@gmail.com>
License: MIT License
Project-URL: Homepage, https://github.com/mcboman/aio-easy-rabbit
Project-URL: Bug Tracker, https://github.com/mcboman/aio-easy-rabbit/issues
Classifier: Programming Language :: Python :: 3
Classifier: License :: OSI Approved :: MIT License
Classifier: Operating System :: OS Independent
Requires-Python: >3.10
License-File: LICENSE
